mcvqoe/mouth2ear/__init__.py
mcvqoe/mouth2ear/m2e.py
mcvqoe/mouth2ear/m2e_eval.py
mcvqoe/mouth2ear/m2e_hw_test.py
mcvqoe/mouth2ear/m2e_reprocess.py
mcvqoe/mouth2ear/m2e_simulate.py
mcvqoe/mouth2ear/version.py
mcvqoe/mouth2ear/audio_clips/F1_harvard_phrases.wav
mcvqoe/mouth2ear/audio_clips/F2_harvard_phrases.wav
mcvqoe/mouth2ear/audio_clips/M1_harvard_phrases.wav
mcvqoe/mouth2ear/audio_clips/M2_harvard_phrases.wav
mcvqoe/mouth2ear/audio_clips/__init__.py
mcvqoe_mouth2ear-2.1.3.dist-info/LICENSE.md
mcvqoe_mouth2ear-2.1.3.dist-info/METADATA
mcvqoe_mouth2ear-2.1.3.dist-info/WHEEL
mcvqoe_mouth2ear-2.1.3.dist-info/entry_points.txt
mcvqoe_mouth2ear-2.1.3.dist-info/top_level.txt
mcvqoe_mouth2ear-2.1.3.dist-info/RECORD
