Metadata-Version: 2.2
Name: mcvqoe-mouth2ear
Version: 2.1.3
Summary: Measurement code for measuring mouth to ear latency
Home-page: https://github.com/usnistgov/mouth2ear
Author: PSCR
Author-email: PSCR@PSCR.gov
License: NIST software License
Classifier: Programming Language :: Python :: 3
Classifier: License :: Public Domain
Classifier: Operating System :: OS Independent
Requires-Python: >=3.6
License-File: LICENSE.md
Requires-Dist: mcvqoe-base
Requires-Dist: plotly
Requires-Dist: pandas
Requires-Dist: numpy
Dynamic: author
Dynamic: author-email
Dynamic: classifier
Dynamic: description
Dynamic: description-content-type
Dynamic: home-page
Dynamic: license
Dynamic: requires-dist
Dynamic: requires-python
Dynamic: summary
